cirrus_client/__init__.py
cirrus_client/__main__.py
cirrus_client/about.py
cirrus_client-0.2.1.1.dist-info/METADATA
cirrus_client-0.2.1.1.dist-info/WHEEL
cirrus_client-0.2.1.1.dist-info/entry_points.txt
cirrus_client-0.2.1.1.dist-info/top_level.txt
cirrus_client-0.2.1.1.dist-info/RECORD
