Metadata-Version: 2.1
Name: cirrus-client
Version: 0.2.1.1
Summary: Global Maksimum Cirrus Client API.
Home-page: https://github.com/GlobalMaksimum/cirrus-client
Author: Global Maksimum Infrastructure
Author-email: info@globalmaksimum.com
License: MIT
Platform: UNKNOWN
Classifier: Development Status :: 3 - Alpha
Classifier: Environment :: Console
Classifier: Intended Audience :: Information Technology
Classifier: Intended Audience :: System Administrators
Classifier: Intended Audience :: Developers
Classifier: License :: OSI Approved :: MIT License
Classifier: Operating System :: POSIX :: Linux
Classifier: Operating System :: MacOS :: MacOS X
Classifier: Operating System :: Microsoft :: Windows
Classifier: Programming Language :: Python :: 3.6
Classifier: Programming Language :: Python :: 3.7
Classifier: Programming Language :: Python :: 3.8
Classifier: Topic :: System
Classifier: Topic :: System :: Installation/Setup
Classifier: Topic :: System :: Networking
Classifier: Topic :: System :: Filesystems
Classifier: Topic :: System :: Hardware
Classifier: Topic :: System :: Operating System
Requires-Python: >=3.6
Requires-Dist: click
Requires-Dist: rich
Requires-Dist: requests
